Metadata-Version: 2.1
Name: LuBanPy
Version: 0.4.112
Summary: LuBanPy是一套通用的Python开发辅助脚手架工具套件
Home-page: https://github.com/oneincloud/LuBanPy
Author: Alex
Author-email: alex@one-in-cloud.com
License: UNKNOWN
Keywords: 脚手架,跨平台,web框架,api框架,qt框架,事件系统,AES加密解密,RSA加密解密,sql生成,orm框架
Platform: UNKNOWN
Classifier: Development Status :: 3 - Alpha
Classifier: Intended Audience :: Developers
Classifier: Topic :: Software Development :: Build Tools
Classifier: Programming Language :: Python :: 3.8
Classifier: Programming Language :: Python :: 3.9
Classifier: Programming Language :: Python :: 3.10
License-File: LICENSE
